{
  "schema_version": "x_make_github_clones_x.run/1.0",
  "run_id": "f8e4daa761c64008a5f982a0717b494b",
  "started_at": "2025-11-02T22:39:53Z",
  "completed_at": "2025-11-02T22:40:50Z",
  "duration_seconds": 56.51,
  "invocation": {
    "username": "eye4357",
    "target_dir": "C:\\x_runner_x",
    "shallow": false,
    "include_forks": false,
    "force_reclone": false,
    "names_filter": null,
    "include_private": true,
    "token_provided": true,
    "allow_token_clone": false
  },
  "summary": {
    "total_repos": 24,
    "successful": 22,
    "missing_clone_url": 0,
    "failed_updates": 2,
    "fetch_error": null,
    "failed_repos": [
      "x_make_cli_scaffolder_x",
      "x_make_contract_validators_x"
    ]
  },
  "repos": [
    {
      "name": "x_make_cli_scaffolder_x",
      "full_name": "eye4357/x_make_cli_scaffolder_x",
      "target_path": "C:\\x_runner_x\\x_make_cli_scaffolder_x",
      "source_https": "https://github.com/eye4357/x_make_cli_scaffolder_x.git",
      "source_ssh": "git@github.com:eye4357/x_make_cli_scaffolder_x.git",
      "used_token_clone": false,
      "status": "failed",
      "duration_seconds": 2.382,
      "error": "clone_or_update_failed"
    },
    {
      "name": "x_make_common_x",
      "full_name": "eye4357/x_make_common_x",
      "target_path": "C:\\x_runner_x\\x_make_common_x",
      "source_https": "https://github.com/eye4357/x_make_common_x.git",
      "source_ssh": "git@github.com:eye4357/x_make_common_x.git",
      "used_token_clone": false,
      "status": "updated",
      "duration_seconds": 1.417
    },
    {
      "name": "x_make_contract_validators_x",
      "full_name": "eye4357/x_make_contract_validators_x",
      "target_path": "C:\\x_runner_x\\x_make_contract_validators_x",
      "source_https": "https://github.com/eye4357/x_make_contract_validators_x.git",
      "source_ssh": "git@github.com:eye4357/x_make_contract_validators_x.git",
      "used_token_clone": false,
      "status": "failed",
      "duration_seconds": 2.277,
      "error": "clone_or_update_failed"
    },
    {
      "name": "x_make_github_clones_x",
      "full_name": "eye4357/x_make_github_clones_x",
      "target_path": "C:\\x_runner_x\\x_make_github_clones_x",
      "source_https": "https://github.com/eye4357/x_make_github_clones_x.git",
      "source_ssh": "git@github.com:eye4357/x_make_github_clones_x.git",
      "used_token_clone": false,
      "status": "updated",
      "duration_seconds": 1.098
    },
    {
      "name": "x_make_github_visitor_x",
      "full_name": "eye4357/x_make_github_visitor_x",
      "target_path": "C:\\x_runner_x\\x_make_github_visitor_x",
      "source_https": "https://github.com/eye4357/x_make_github_visitor_x.git",
      "source_ssh": "git@github.com:eye4357/x_make_github_visitor_x.git",
      "used_token_clone": false,
      "status": "updated",
      "duration_seconds": 1.925
    },
    {
      "name": "x_make_graphviz_x",
      "full_name": "eye4357/x_make_graphviz_x",
      "target_path": "C:\\x_runner_x\\x_make_graphviz_x",
      "source_https": "https://github.com/eye4357/x_make_graphviz_x.git",
      "source_ssh": "git@github.com:eye4357/x_make_graphviz_x.git",
      "used_token_clone": false,
      "status": "updated",
      "duration_seconds": 1.059
    },
    {
      "name": "x_make_markdown_x",
      "full_name": "eye4357/x_make_markdown_x",
      "target_path": "C:\\x_runner_x\\x_make_markdown_x",
      "source_https": "https://github.com/eye4357/x_make_markdown_x.git",
      "source_ssh": "git@github.com:eye4357/x_make_markdown_x.git",
      "used_token_clone": false,
      "status": "updated",
      "duration_seconds": 0.977
    },
    {
      "name": "x_make_mermaid_x",
      "full_name": "eye4357/x_make_mermaid_x",
      "target_path": "C:\\x_runner_x\\x_make_mermaid_x",
      "source_https": "https://github.com/eye4357/x_make_mermaid_x.git",
      "source_ssh": "git@github.com:eye4357/x_make_mermaid_x.git",
      "used_token_clone": false,
      "status": "updated",
      "duration_seconds": 1.004
    },
    {
      "name": "x_make_persistent_env_var_x",
      "full_name": "eye4357/x_make_persistent_env_var_x",
      "target_path": "C:\\x_runner_x\\x_make_persistent_env_var_x",
      "source_https": "https://github.com/eye4357/x_make_persistent_env_var_x.git",
      "source_ssh": "git@github.com:eye4357/x_make_persistent_env_var_x.git",
      "used_token_clone": false,
      "status": "updated",
      "duration_seconds": 1.655
    },
    {
      "name": "x_make_pip_updates_x",
      "full_name": "eye4357/x_make_pip_updates_x",
      "target_path": "C:\\x_runner_x\\x_make_pip_updates_x",
      "source_https": "https://github.com/eye4357/x_make_pip_updates_x.git",
      "source_ssh": "git@github.com:eye4357/x_make_pip_updates_x.git",
      "used_token_clone": false,
      "status": "updated",
      "duration_seconds": 2.593
    },
    {
      "name": "x_make_progress_board_x",
      "full_name": "eye4357/x_make_progress_board_x",
      "target_path": "C:\\x_runner_x\\x_make_progress_board_x",
      "source_https": "https://github.com/eye4357/x_make_progress_board_x.git",
      "source_ssh": "git@github.com:eye4357/x_make_progress_board_x.git",
      "used_token_clone": false,
      "status": "updated",
      "duration_seconds": 1.404
    },
    {
      "name": "x_make_pypi_x",
      "full_name": "eye4357/x_make_pypi_x",
      "target_path": "C:\\x_runner_x\\x_make_pypi_x",
      "source_https": "https://github.com/eye4357/x_make_pypi_x.git",
      "source_ssh": "git@github.com:eye4357/x_make_pypi_x.git",
      "used_token_clone": false,
      "status": "updated",
      "duration_seconds": 1.805
    },
    {
      "name": "x_make_py_mod_sideload_x",
      "full_name": "eye4357/x_make_py_mod_sideload_x",
      "target_path": "C:\\x_runner_x\\x_make_py_mod_sideload_x",
      "source_https": "https://github.com/eye4357/x_make_py_mod_sideload_x.git",
      "source_ssh": "git@github.com:eye4357/x_make_py_mod_sideload_x.git",
      "used_token_clone": false,
      "status": "updated",
      "duration_seconds": 1.747
    },
    {
      "name": "x_make_py_venv_x",
      "full_name": "eye4357/x_make_py_venv_x",
      "target_path": "C:\\x_runner_x\\x_make_py_venv_x",
      "source_https": "https://github.com/eye4357/x_make_py_venv_x.git",
      "source_ssh": "git@github.com:eye4357/x_make_py_venv_x.git",
      "used_token_clone": false,
      "status": "updated",
      "duration_seconds": 1.325
    },
    {
      "name": "x_make_slack_dump_and_reset_z",
      "full_name": "eye4357/x_make_slack_dump_and_reset_z",
      "target_path": "C:\\x_runner_x\\x_make_slack_dump_and_reset_z",
      "source_https": "https://github.com/eye4357/x_make_slack_dump_and_reset_z.git",
      "source_ssh": "git@github.com:eye4357/x_make_slack_dump_and_reset_z.git",
      "used_token_clone": false,
      "status": "updated",
      "duration_seconds": 1.342
    },
    {
      "name": "x_make_yahw_x",
      "full_name": "eye4357/x_make_yahw_x",
      "target_path": "C:\\x_runner_x\\x_make_yahw_x",
      "source_https": "https://github.com/eye4357/x_make_yahw_x.git",
      "source_ssh": "git@github.com:eye4357/x_make_yahw_x.git",
      "used_token_clone": false,
      "status": "updated",
      "duration_seconds": 1.333
    },
    {
      "name": "x_0_make_all_x",
      "full_name": "eye4357/x_0_make_all_x",
      "target_path": "C:\\x_runner_x\\x_0_make_all_x",
      "source_https": "https://github.com/eye4357/x_0_make_all_x.git",
      "source_ssh": "git@github.com:eye4357/x_0_make_all_x.git",
      "used_token_clone": false,
      "status": "updated",
      "duration_seconds": 4.243
    },
    {
      "name": "x_0_make_ppnw_dot_ai_x",
      "full_name": "eye4357/x_0_make_ppnw_dot_ai_x",
      "target_path": "C:\\x_runner_x\\x_0_make_ppnw_dot_ai_x",
      "source_https": "https://github.com/eye4357/x_0_make_ppnw_dot_ai_x.git",
      "source_ssh": "git@github.com:eye4357/x_0_make_ppnw_dot_ai_x.git",
      "used_token_clone": false,
      "status": "updated",
      "duration_seconds": 3.832
    },
    {
      "name": "x_0_run_all_x",
      "full_name": "eye4357/x_0_run_all_x",
      "target_path": "C:\\x_runner_x\\x_0_run_all_x",
      "source_https": "https://github.com/eye4357/x_0_run_all_x.git",
      "source_ssh": "git@github.com:eye4357/x_0_run_all_x.git",
      "used_token_clone": false,
      "status": "updated",
      "duration_seconds": 3.773
    },
    {
      "name": "x_legatus_acta_schedae_x",
      "full_name": "eye4357/x_legatus_acta_schedae_x",
      "target_path": "C:\\x_runner_x\\x_legatus_acta_schedae_x",
      "source_https": "https://github.com/eye4357/x_legatus_acta_schedae_x.git",
      "source_ssh": "git@github.com:eye4357/x_legatus_acta_schedae_x.git",
      "used_token_clone": false,
      "status": "updated",
      "duration_seconds": 3.054
    },
    {
      "name": "x_legatus_capsula_calculus_x",
      "full_name": "eye4357/x_legatus_capsula_calculus_x",
      "target_path": "C:\\x_runner_x\\x_legatus_capsula_calculus_x",
      "source_https": "https://github.com/eye4357/x_legatus_capsula_calculus_x.git",
      "source_ssh": "git@github.com:eye4357/x_legatus_capsula_calculus_x.git",
      "used_token_clone": false,
      "status": "updated",
      "duration_seconds": 3.913
    },
    {
      "name": "x_legatus_celer_notitia_x",
      "full_name": "eye4357/x_legatus_celer_notitia_x",
      "target_path": "C:\\x_runner_x\\x_legatus_celer_notitia_x",
      "source_https": "https://github.com/eye4357/x_legatus_celer_notitia_x.git",
      "source_ssh": "git@github.com:eye4357/x_legatus_celer_notitia_x.git",
      "used_token_clone": false,
      "status": "updated",
      "duration_seconds": 3.438
    },
    {
      "name": "x_legatus_tactica_impetus_x",
      "full_name": "eye4357/x_legatus_tactica_impetus_x",
      "target_path": "C:\\x_runner_x\\x_legatus_tactica_impetus_x",
      "source_https": "https://github.com/eye4357/x_legatus_tactica_impetus_x.git",
      "source_ssh": "git@github.com:eye4357/x_legatus_tactica_impetus_x.git",
      "used_token_clone": false,
      "status": "updated",
      "duration_seconds": 3.597
    },
    {
      "name": "x_legatus_vigil_nexus_x",
      "full_name": "eye4357/x_legatus_vigil_nexus_x",
      "target_path": "C:\\x_runner_x\\x_legatus_vigil_nexus_x",
      "source_https": "https://github.com/eye4357/x_legatus_vigil_nexus_x.git",
      "source_ssh": "git@github.com:eye4357/x_legatus_vigil_nexus_x.git",
      "used_token_clone": false,
      "status": "updated",
      "duration_seconds": 3.345
    }
  ],
  "exit_code": 3,
  "tool": "x_make_github_clones_x",
  "generated_at": "2025-11-02T22:40:50Z"
}